Metadata-Version: 1.0
Name: dst-gausbin
Version: 0.2
Summary: Gaussian and binomial distributions
Home-page: UNKNOWN
Author: Philipp Schmalen
Author-email: philbf@gmx.de
License: UNKNOWN
Platform: UNKNOWN
